smiet/__init__.py
smiet/units.py
smiet/corsika/__init__.py
smiet/corsika/generate_file_contents.py
smiet/corsika/write_simulation.py
smiet/jax/__init__.py
smiet/jax/synthesis.py
smiet/jax/io/__init__.py
smiet/jax/io/base_shower.py
smiet/jax/io/coreas_hdf5.py
smiet/jax/io/sliced_shower.py
smiet/jax/utilities/__init__.py
smiet/jax/utilities/batched_interpolation.py
smiet/jax/utilities/geometry.py
smiet/jax/utilities/jax_utils.py
smiet/jax/utilities/utilities.py
smiet/numpy/__init__.py
smiet/numpy/synthesis.py
smiet/numpy/io/__init__.py
smiet/numpy/io/base_shower.py
smiet/numpy/io/coreas_shower.py
smiet/numpy/io/sliced_shower.py
smiet/numpy/utilities/__init__.py
smiet/numpy/utilities/cs_transformations.py
smiet/numpy/utilities/geometry.py
smiet/numpy/utilities/trace_utils.py
smiet/spectral_parameters/spectral_parameters_30_500_100.hdf5
smiet/spectral_parameters/spectral_parameters_30_80_50.hdf5
smiet/templates/.gitkeep
smiet-0.6.0.dist-info/licenses/LICENSE
smiet-0.6.0.dist-info/METADATA
smiet-0.6.0.dist-info/WHEEL
smiet-0.6.0.dist-info/top_level.txt
smiet-0.6.0.dist-info/RECORD
