Metadata-Version: 2.4
Name: smiet
Version: 0.6.0
Summary: Implementation of the template synthesis framework for cosmic-ray air showers
Author-email: Mitja Desmet <mitja.desmet@vub.be>, Keito Watanabe <keito.watanabe@kit.edu>
License-Expression: GPL-3.0-or-later
Project-URL: Documentation, https://web.iap.kit.edu/huege/smiet/
Project-URL: Repository, https://gitlab.iap.kit.edu/AirShowerPhysics/smiet-cr-synthesis/
Project-URL: Issues, https://gitlab.iap.kit.edu/AirShowerPhysics/smiet-cr-synthesis/-/issues
Keywords: cosmic,ray,template,synthesis
Requires-Python: >=3.8
License-File: LICENSE
Requires-Dist: numpy>=1.20
Requires-Dist: scipy>=1.8
Requires-Dist: h5py
Requires-Dist: typing-extensions>=4.7
Requires-Dist: radiotools
Provides-Extra: tests
Requires-Dist: matplotlib; extra == "tests"
Provides-Extra: dev
Requires-Dist: sphinx; extra == "dev"
Requires-Dist: sphinx-immaterial; extra == "dev"
Requires-Dist: numpydoc; extra == "dev"
Provides-Extra: jax
Requires-Dist: jax; extra == "jax"
Requires-Dist: jaxlib; extra == "jax"
Requires-Dist: jax_radio_tools; extra == "jax"
Dynamic: license-file
